README.md
pyproject.toml
setup.py
DeterministicParticleFlowControl/DeterministicParticleFlowControl.py
DeterministicParticleFlowControl/__init__.py
DeterministicParticleFlowControl/due.py
DeterministicParticleFlowControl/script_1.py
DeterministicParticleFlowControl/testing_kernel.py
DeterministicParticleFlowControl/version.py
DeterministicParticleFlowControl.egg-info/PKG-INFO
DeterministicParticleFlowControl.egg-info/SOURCES.txt
DeterministicParticleFlowControl.egg-info/dependency_links.txt
DeterministicParticleFlowControl.egg-info/requires.txt
DeterministicParticleFlowControl.egg-info/top_level.txt
DeterministicParticleFlowControl/data/thumbnail2.png
DeterministicParticleFlowControl/reweighting/__init__.py
DeterministicParticleFlowControl/reweighting/optimal_transport_reweighting.py
DeterministicParticleFlowControl/score_estimators/__init__.py
DeterministicParticleFlowControl/score_estimators/score.py
DeterministicParticleFlowControl/score_estimators/score_function_estimators.py
DeterministicParticleFlowControl/tests/__init__.py
DeterministicParticleFlowControl/tests/test_cdist.py
DeterministicParticleFlowControl/tests/testing1.py