Metadata-Version: 2.1
Name: DeterministicParticleFlowControl
Version: 0.3.2
Summary: DeterministicParticleFlowControl: deterministic particle based stochastic optimal control framework
Home-page: https://github.com/dimitra-maoutsa/DeterministicParticleFlowControl
Author: Dimitra Maoutsa
Author-email: dimitra.maoutsa@tu-berlin.de
Maintainer: Dimitra Maoutsa
Maintainer-email: dimitra.maoutsa@gmail.com
License: MIT
Download-URL: https://github.com/dimitra-maoutsa/DeterministicParticleFlowControl/archive/refs/tags/v0.1.1.tar.gz
Platform: OS Independent
Classifier: Development Status :: 3 - Alpha
Classifier: Environment :: Console
Classifier: Intended Audience :: Science/Research
Classifier: License :: OSI Approved :: MIT License
Classifier: Operating System :: OS Independent
Classifier: Programming Language :: Python
Classifier: Topic :: Scientific/Engineering
Requires: numpy
Requires: scipy
Requires: matplotlib
Requires: numba
Requires: POT
Requires: pyemd
Requires: duecredit
Requires: seaborn
Requires-Python: >= 3.5
